gridworldpy/__init__.py
gridworldpy/gridworld.py
gridworldpy/q_table.py
gridworldpy/utils.py
gridworldpy-0.2.0.dist-info/LICENSE
gridworldpy-0.2.0.dist-info/METADATA
gridworldpy-0.2.0.dist-info/WHEEL
gridworldpy-0.2.0.dist-info/top_level.txt
gridworldpy-0.2.0.dist-info/RECORD
