Metadata-Version: 2.1
Name: gridworldpy
Version: 0.2.0
Summary: A flexible and interactive grid world environment for reinforcement learning
Home-page: https://github.com/hitlic/gridworldpy
Author: LIC
Author-email: LIC <liuchen.lic@gmail.com>
Maintainer-email: LIC <liuchen.lic@gmail.com>
License: MIT
Project-URL: Homepage, https://github.com/hitlic/gridworldpy
Project-URL: Repository, https://github.com/hitlic/gridworldpy
Project-URL: Documentation, https://github.com/hitlic/gridworldpy#readme
Project-URL: Bug Reports, https://github.com/hitlic/gridworldpy/issues
Keywords: reinforcement learning,grid world,environment,RL,AI,machine learning,visualization
Classifier: Development Status :: 4 - Beta
Classifier: Intended Audience :: Developers
Classifier: Intended Audience :: Education
Classifier: Intended Audience :: Science/Research
Classifier: Operating System :: OS Independent
Classifier: Programming Language :: Python :: 3
Classifier: Programming Language :: Python :: 3.8
Classifier: Programming Language :: Python :: 3.9
Classifier: Programming Language :: Python :: 3.10
Classifier: Programming Language :: Python :: 3.11
Classifier: Programming Language :: Python :: 3.12
Classifier: Topic :: Scientific/Engineering :: Artificial Intelligence
Classifier: Topic :: Software Development :: Libraries :: Python Modules
Requires-Python: >=3.8
License-File: LICENSE
Requires-Dist: numpy >=1.21.0
Provides-Extra: examples
Requires-Dist: matplotlib >=3.5.0 ; extra == 'examples'
